cv_model/__init__.py
cv_model/predict.py
cv_model-1.4.0.dist-info/LICENSE
cv_model-1.4.0.dist-info/METADATA
cv_model-1.4.0.dist-info/WHEEL
cv_model-1.4.0.dist-info/entry_points.txt
cv_model-1.4.0.dist-info/RECORD
