Metadata-Version: 2.3
Name: cv_model
Version: 1.4.0
Summary: 
Author: Dariusz Homa
Author-email: dariuszhoma7@gmail.com
Requires-Python: >=3.12,<4.0
Classifier: Programming Language :: Python :: 3
Classifier: Programming Language :: Python :: 3.12
Classifier: Programming Language :: Python :: 3.13
Requires-Dist: argparse (>=1.4.0,<2.0.0)
Requires-Dist: bs4 (>=0.0.2,<0.0.3)
Requires-Dist: matplotlib (>=3.10.1,<4.0.0)
Requires-Dist: nltk (>=3.9.1,<4.0.0)
Requires-Dist: numpy (>=2.2.4,<3.0.0)
Requires-Dist: pandas (>=2.2.3,<3.0.0)
Requires-Dist: scikit-learn (>=1.6.1,<2.0.0)
Requires-Dist: transformers (>=4.50.3,<5.0.0)
Requires-Dist: wordcloud (>=1.9.4,<2.0.0)
